app.py
tmux_res-0.4.8.dist-info/LICENSE
tmux_res-0.4.8.dist-info/METADATA
tmux_res-0.4.8.dist-info/WHEEL
tmux_res-0.4.8.dist-info/entry_points.txt
tmux_res-0.4.8.dist-info/top_level.txt
tmux_res-0.4.8.dist-info/RECORD
