Metadata-Version: 2.1
Name: tmux-res
Version: 0.4.8
Summary: Handles your tmux resurrect files
Home-page: UNKNOWN
Author: Alexander Hultnér
Author-email: ahultner@gmail.com
License: UNKNOWN
Platform: UNKNOWN
Classifier: Development Status :: 4 - Beta
Classifier: Intended Audience :: Developers
Classifier: License :: OSI Approved :: BSD License
Classifier: Operating System :: OS Independent
Classifier: Programming Language :: Python
Classifier: Programming Language :: Python :: 3.7
Requires-Python: >=3.7
Requires-Dist: Click
Requires-Dist: python-dotenv
